odoo9_addon_stock_warehouse_orderpoint_stock_info-9.0.1.0.0-py2.7-nspkg.pth
odoo_addons/stock_warehouse_orderpoint_stock_info/__openerp__.py
odoo_addons/stock_warehouse_orderpoint_stock_info/__init__.py
odoo_addons/stock_warehouse_orderpoint_stock_info/README.rst
odoo_addons/stock_warehouse_orderpoint_stock_info/models/__init__.py
odoo_addons/stock_warehouse_orderpoint_stock_info/models/stock_warehouse_orderpoint.py
odoo_addons/stock_warehouse_orderpoint_stock_info/i18n/nl_NL.po
odoo_addons/stock_warehouse_orderpoint_stock_info/i18n/zh_CN.po
odoo_addons/stock_warehouse_orderpoint_stock_info/i18n/tr_TR.po
odoo_addons/stock_warehouse_orderpoint_stock_info/i18n/pt.po
odoo_addons/stock_warehouse_orderpoint_stock_info/i18n/fr_CH.po
odoo_addons/stock_warehouse_orderpoint_stock_info/i18n/it.po
odoo_addons/stock_warehouse_orderpoint_stock_info/i18n/es.po
odoo_addons/stock_warehouse_orderpoint_stock_info/i18n/fr_FR.po
odoo_addons/stock_warehouse_orderpoint_stock_info/i18n/vi_VN.po
odoo_addons/stock_warehouse_orderpoint_stock_info/i18n/ro.po
odoo_addons/stock_warehouse_orderpoint_stock_info/i18n/tr.po
odoo_addons/stock_warehouse_orderpoint_stock_info/i18n/hr.po
odoo_addons/stock_warehouse_orderpoint_stock_info/i18n/gl.po
odoo_addons/stock_warehouse_orderpoint_stock_info/i18n/ca.po
odoo_addons/stock_warehouse_orderpoint_stock_info/i18n/sl.po
odoo_addons/stock_warehouse_orderpoint_stock_info/i18n/es_ES.po
odoo_addons/stock_warehouse_orderpoint_stock_info/i18n/nl.po
odoo_addons/stock_warehouse_orderpoint_stock_info/i18n/de.po
odoo_addons/stock_warehouse_orderpoint_stock_info/i18n/fr.po
odoo_addons/stock_warehouse_orderpoint_stock_info/i18n/pt_BR.po
odoo_addons/stock_warehouse_orderpoint_stock_info/i18n/el_GR.po
odoo_addons/stock_warehouse_orderpoint_stock_info/i18n/es_MX.po
odoo_addons/stock_warehouse_orderpoint_stock_info/i18n/fi.po
odoo_addons/stock_warehouse_orderpoint_stock_info/i18n/hr_HR.po
odoo9_addon_stock_warehouse_orderpoint_stock_info-9.0.1.0.0.dist-info/top_level.txt
odoo9_addon_stock_warehouse_orderpoint_stock_info-9.0.1.0.0.dist-info/WHEEL
odoo9_addon_stock_warehouse_orderpoint_stock_info-9.0.1.0.0.dist-info/RECORD
odoo9_addon_stock_warehouse_orderpoint_stock_info-9.0.1.0.0.dist-info/metadata.json
odoo9_addon_stock_warehouse_orderpoint_stock_info-9.0.1.0.0.dist-info/DESCRIPTION.rst
odoo9_addon_stock_warehouse_orderpoint_stock_info-9.0.1.0.0.dist-info/METADATA
odoo9_addon_stock_warehouse_orderpoint_stock_info-9.0.1.0.0.dist-info/namespace_packages.txt
